{"@module":"pymatgen.core.structure","@class":"Structure","charge":0,"lattice":{"matrix":[[4.766176,0.0,0.0],[0.0,4.766176,0.0],[0.0,0.0,4.766176]],"pbc":[true,true,true],"a":4.766176,"b":4.766176,"c":4.766176,"alpha":90.0,"beta":90.0,"gamma":90.0,"volume":108.27052093006829},"properties":{},"sites":[{"species":[{"element":"Ge","occu":1}],"abc":[0.0,0.5,0.5],"properties":{"magmom":0.0},"label":"Ge","xyz":[0.0,2.383088,2.383088]},{"species":[{"element":"Ge","occu":1}],"abc":[0.5,0.5,0.0],"properties":{"magmom":0.0},"label":"Ge","xyz":[2.383088,2.383088,0.0]},{"species":[{"element":"Ge","occu":1}],"abc":[0.5,0.0,0.5],"properties":{"magmom":0.0},"label":"Ge","xyz":[2.383088,0.0,2.383088]},{"species":[{"element":"Ge","occu":1}],"abc":[0.0,0.0,0.0],"properties":{"magmom":0.0},"label":"Ge","xyz":[0.0,0.0,0.0]},{"species":[{"element":"O","occu":1}],"abc":[0.343148,0.156852,0.843148],"properties":{"magmom":0.0},"label":"O","xyz":[1.635503762048,0.7475842379519999,4.018591762048]},{"species":[{"element":"O","occu":1}],"abc":[0.156852,0.843148,0.343148],"properties":{"magmom":0.0},"label":"O","xyz":[0.7475842379519999,4.018591762048,1.635503762048]},{"species":[{"element":"O","occu":1}],"abc":[0.843148,0.343148,0.156852],"properties":{"magmom":0.0},"label":"O","xyz":[4.018591762048,1.635503762048,0.7475842379519999]},{"species":[{"element":"O","occu":1}],"abc":[0.656852,0.656852,0.656852],"properties":{"magmom":0.0},"label":"O","xyz":[3.130672237952,3.130672237952,3.130672237952]},{"species":[{"element":"O","occu":1}],"abc":[0.343148,0.343148,0.343148],"properties":{"magmom":0.0},"label":"O","xyz":[1.635503762048,1.635503762048,1.635503762048]},{"species":[{"element":"O","occu":1}],"abc":[0.156852,0.656852,0.843148],"properties":{"magmom":0.0},"label":"O","xyz":[0.7475842379519999,3.130672237952,4.018591762048]},{"species":[{"element":"O","occu":1}],"abc":[0.843148,0.156852,0.656852],"properties":{"magmom":0.0},"label":"O","xyz":[4.018591762048,0.7475842379519999,3.130672237952]},{"species":[{"element":"O","occu":1}],"abc":[0.656852,0.843148,0.156852],"properties":{"magmom":0.0},"label":"O","xyz":[3.130672237952,4.018591762048,0.7475842379519999]}]}