{"@module":"pymatgen.core.structure","@class":"Structure","charge":0,"lattice":{"matrix":[[8.69165083,0.0,0.0],[0.0,8.68006673,0.0],[0.0,0.0,4.43717411]],"pbc":[true,true,true],"a":8.69165083,"b":8.68006673,"c":4.43717411,"alpha":90.0,"beta":90.0,"gamma":90.0,"volume":334.75864808653165},"properties":{},"sites":[{"species":[{"element":"K","occu":1}],"abc":[0.00068115,0.0,0.0],"properties":{"magmom":-0.0},"label":"K","xyz":[0.005920317962854501,0.0,0.0]},{"species":[{"element":"Hf","occu":1}],"abc":[0.49330539,0.5,0.0],"properties":{"magmom":0.161},"label":"Hf","xyz":[4.287638202436974,4.340033365,0.0]},{"species":[{"element":"Mg","occu":1}],"abc":[0.99675334,0.5,0.0],"properties":{"magmom":-0.001},"label":"Mg","xyz":[8.663431994916273,4.340033365,0.0]},{"species":[{"element":"Mg","occu":1}],"abc":[0.50048602,0.0,0.0],"properties":{"magmom":-0.0},"label":"Mg","xyz":[4.350049731136396,0.0,0.0]},{"species":[{"element":"Mg","occu":1}],"abc":[0.00102684,0.24980172,0.5],"properties":{"magmom":0.0},"label":"Mg","xyz":[0.0089249347382772,2.1682955988687755,2.218587055]},{"species":[{"element":"Mg","occu":1}],"abc":[0.00102684,0.75019828,0.5],"properties":{"magmom":0.0},"label":"Mg","xyz":[0.0089249347382772,6.5117711311312245,2.218587055]},{"species":[{"element":"Mg","occu":1}],"abc":[0.49886435,0.2402503,0.5],"properties":{"magmom":0.0},"label":"Mg","xyz":[4.335954741734911,2.085388635902519,2.218587055]},{"species":[{"element":"Mg","occu":1}],"abc":[0.49886435,0.7597497,0.5],"properties":{"magmom":0.0},"label":"Mg","xyz":[4.335954741734911,6.594678094097481,2.218587055]},{"species":[{"element":"Mg","occu":1}],"abc":[0.24832379000000002,0.0,0.5],"properties":{"magmom":0.001},"label":"Mg","xyz":[2.158343675462246,0.0,2.218587055]},{"species":[{"element":"Mg","occu":1}],"abc":[0.244941,0.5,0.5],"properties":{"magmom":0.014},"label":"Mg","xyz":[2.12894164595103,4.340033365,2.218587055]},{"species":[{"element":"Mg","occu":1}],"abc":[0.75173342,0.0,0.5],"properties":{"magmom":0.0},"label":"Mg","xyz":[6.533804403881739,0.0,2.218587055]},{"species":[{"element":"Mg","occu":1}],"abc":[0.75801611,0.5,0.5],"properties":{"magmom":0.001},"label":"Mg","xyz":[6.588411351634872,4.340033365,2.218587055]},{"species":[{"element":"Mg","occu":1}],"abc":[0.24189462,0.24313345,-0.0],"properties":{"magmom":-0.0},"label":"Mg","xyz":[2.102463574695535,2.1104145702951187,0.0]},{"species":[{"element":"Mg","occu":1}],"abc":[0.24189462,0.75686655,0.0],"properties":{"magmom":-0.0},"label":"Mg","xyz":[2.102463574695535,6.569652159704882,0.0]},{"species":[{"element":"Mg","occu":1}],"abc":[0.75784393,0.24569862,0.0],"properties":{"magmom":-0.0},"label":"Mg","xyz":[6.586914823194963,2.132680417068913,0.0]},{"species":[{"element":"Mg","occu":1}],"abc":[0.75784393,0.75430138,-0.0],"properties":{"magmom":-0.0},"label":"Mg","xyz":[6.586914823194963,6.547386312931088,0.0]},{"species":[{"element":"O","occu":1}],"abc":[0.27716105,0.0,0.0],"properties":{"magmom":0.001},"label":"O","xyz":[2.4089870702761718,0.0,0.0]},{"species":[{"element":"O","occu":1}],"abc":[0.7239423500000001,0.0,0.0],"properties":{"magmom":-0.0},"label":"O","xyz":[6.2922541272496515,0.0,0.0]},{"species":[{"element":"O","occu":1}],"abc":[0.748389299999999,0.5,0.0],"properties":{"magmom":0.003},"label":"O","xyz":[6.504738480508111,4.340033365,0.0]},{"species":[{"element":"O","occu":1}],"abc":[0.25102918,0.24411175000000002,0.5],"properties":{"magmom":0.004},"label":"O","xyz":[2.1818579807012197,2.1189062795770774,2.218587055]},{"species":[{"element":"O","occu":1}],"abc":[0.25102918,0.75588825,0.5],"properties":{"magmom":0.004},"label":"O","xyz":[2.1818579807012197,6.561160450422923,2.218587055]},{"species":[{"element":"O","occu":1}],"abc":[0.74792778,0.25060076,0.5],"properties":{"magmom":0.0},"label":"O","xyz":[6.500727109817058,2.1752313193887147,2.218587055]},{"species":[{"element":"O","occu":1}],"abc":[0.74792778,0.74939924,0.5],"properties":{"magmom":0.0},"label":"O","xyz":[6.500727109817058,6.504835410611285,2.218587055]},{"species":[{"element":"O","occu":1}],"abc":[0.99753347,0.0,0.5],"properties":{"magmom":0.0},"label":"O","xyz":[8.67021261247828,0.0,2.218587055]},{"species":[{"element":"O","occu":1}],"abc":[0.999317599999999,0.5,0.5],"properties":{"magmom":0.001},"label":"O","xyz":[8.6857196474736,4.340033365,2.218587055]},{"species":[{"element":"O","occu":1}],"abc":[0.50116444,0.0,0.5],"properties":{"magmom":0.0},"label":"O","xyz":[4.355946320892485,0.0,2.218587055]},{"species":[{"element":"O","occu":1}],"abc":[0.5075294300000001,0.5,0.5],"properties":{"magmom":0.017},"label":"O","xyz":[4.411268591508928,4.340033365,2.218587055]},{"species":[{"element":"O","occu":1}],"abc":[0.00085161,0.27580294,0.0],"properties":{"magmom":-0.0},"label":"O","xyz":[0.007401896763336301,2.393987923530186,0.0]},{"species":[{"element":"O","occu":1}],"abc":[0.00085161,0.7241970600000001,-0.0],"properties":{"magmom":-0.0},"label":"O","xyz":[0.007401896763336301,6.286078806469814,0.0]},{"species":[{"element":"O","occu":1}],"abc":[0.50092275,0.25947896,0.0],"properties":{"magmom":-0.002},"label":"O","xyz":[4.353845635803382,2.2522946878310006,0.0]},{"species":[{"element":"O","occu":1}],"abc":[0.50092275,0.74052104,0.0],"properties":{"magmom":-0.002},"label":"O","xyz":[4.353845635803382,6.427772042168999,0.0]}]}