{"@module":"pymatgen.core.structure","@class":"Structure","charge":0,"lattice":{"matrix":[[8.59842,0.0,0.0],[0.0,8.59842,0.0],[0.0,0.0,8.576041]],"pbc":[true,true,true],"a":8.59842,"b":8.59842,"c":8.576041,"alpha":90.0,"beta":90.0,"gamma":90.0,"volume":634.0509512790129},"properties":{},"sites":[{"species":[{"element":"Mg","occu":1}],"abc":[0.5,0.0,0.0],"properties":{"magmom":0.0},"label":"Mg","xyz":[4.29921,0.0,0.0]},{"species":[{"element":"Mg","occu":1}],"abc":[0.5,0.0,0.5],"properties":{"magmom":0.0},"label":"Mg","xyz":[4.29921,0.0,4.2880205]},{"species":[{"element":"Mg","occu":1}],"abc":[0.0,0.5,0.0],"properties":{"magmom":0.0},"label":"Mg","xyz":[0.0,4.29921,0.0]},{"species":[{"element":"Mg","occu":1}],"abc":[0.0,0.5,0.5],"properties":{"magmom":0.0},"label":"Mg","xyz":[0.0,4.29921,4.2880205]},{"species":[{"element":"Mg","occu":1}],"abc":[0.5,0.5,0.0],"properties":{"magmom":0.0},"label":"Mg","xyz":[4.29921,4.29921,0.0]},{"species":[{"element":"Mg","occu":1}],"abc":[0.5,0.5,0.5],"properties":{"magmom":0.0},"label":"Mg","xyz":[4.29921,4.29921,4.2880205]},{"species":[{"element":"Mg","occu":1}],"abc":[0.254921,0.0,0.245476],"properties":{"magmom":0.0},"label":"Mg","xyz":[2.1919178248200004,0.0,2.105212240516]},{"species":[{"element":"Mg","occu":1}],"abc":[0.254921,0.0,0.754524],"properties":{"magmom":0.0},"label":"Mg","xyz":[2.1919178248200004,0.0,6.470828759484]},{"species":[{"element":"Mg","occu":1}],"abc":[0.745078999999999,0.0,0.245476],"properties":{"magmom":0.0},"label":"Mg","xyz":[6.406502175179993,0.0,2.105212240516]},{"species":[{"element":"Mg","occu":1}],"abc":[0.745078999999999,0.0,0.754524],"properties":{"magmom":0.0},"label":"Mg","xyz":[6.406502175179993,0.0,6.470828759484]},{"species":[{"element":"Mg","occu":1}],"abc":[0.250175,0.5,0.249586],"properties":{"magmom":0.0},"label":"Mg","xyz":[2.1511097235,4.29921,2.140459769026]},{"species":[{"element":"Mg","occu":1}],"abc":[0.250175,0.5,0.750413999999999],"properties":{"magmom":0.0},"label":"Mg","xyz":[2.1511097235,4.29921,6.435581230973992]},{"species":[{"element":"Mg","occu":1}],"abc":[0.749825,0.5,0.249586],"properties":{"magmom":0.0},"label":"Mg","xyz":[6.4473102765000005,4.29921,2.140459769026]},{"species":[{"element":"Mg","occu":1}],"abc":[0.749825,0.5,0.750413999999999],"properties":{"magmom":0.0},"label":"Mg","xyz":[6.4473102765000005,4.29921,6.435581230973992]},{"species":[{"element":"Mg","occu":1}],"abc":[0.0,0.254921,0.245476],"properties":{"magmom":0.0},"label":"Mg","xyz":[0.0,2.1919178248200004,2.105212240516]},{"species":[{"element":"Mg","occu":1}],"abc":[0.0,0.254921,0.754524],"properties":{"magmom":0.0},"label":"Mg","xyz":[0.0,2.1919178248200004,6.470828759484]},{"species":[{"element":"Mg","occu":1}],"abc":[0.5,0.250175,0.249586],"properties":{"magmom":0.0},"label":"Mg","xyz":[4.29921,2.1511097235,2.140459769026]},{"species":[{"element":"Mg","occu":1}],"abc":[0.5,0.250175,0.750413999999999],"properties":{"magmom":0.0},"label":"Mg","xyz":[4.29921,2.1511097235,6.435581230973992]},{"species":[{"element":"Mg","occu":1}],"abc":[0.0,0.745078999999999,0.245476],"properties":{"magmom":0.0},"label":"Mg","xyz":[0.0,6.406502175179993,2.105212240516]},{"species":[{"element":"Mg","occu":1}],"abc":[0.0,0.745078999999999,0.754524],"properties":{"magmom":0.0},"label":"Mg","xyz":[0.0,6.406502175179993,6.470828759484]},{"species":[{"element":"Mg","occu":1}],"abc":[0.5,0.749825,0.249586],"properties":{"magmom":0.0},"label":"Mg","xyz":[4.29921,6.4473102765000005,2.140459769026]},{"species":[{"element":"Mg","occu":1}],"abc":[0.5,0.749825,0.750413999999999],"properties":{"magmom":0.0},"label":"Mg","xyz":[4.29921,6.4473102765000005,6.435581230973992]},{"species":[{"element":"Mg","occu":1}],"abc":[0.25005,0.25005,0.0],"properties":{"magmom":0.0},"label":"Mg","xyz":[2.150034921,2.150034921,0.0]},{"species":[{"element":"Mg","occu":1}],"abc":[0.254235999999999,0.254235999999999,0.5],"properties":{"magmom":0.0},"label":"Mg","xyz":[2.1860279071199917,2.1860279071199917,4.2880205]},{"species":[{"element":"Mg","occu":1}],"abc":[0.7499500000000001,0.25005,0.0],"properties":{"magmom":0.0},"label":"Mg","xyz":[6.448385079000001,2.150034921,0.0]},{"species":[{"element":"Mg","occu":1}],"abc":[0.745764,0.254235999999999,0.5],"properties":{"magmom":0.0},"label":"Mg","xyz":[6.41239209288,2.1860279071199917,4.2880205]},{"species":[{"element":"Mg","occu":1}],"abc":[0.25005,0.7499500000000001,0.0],"properties":{"magmom":0.0},"label":"Mg","xyz":[2.150034921,6.448385079000001,0.0]},{"species":[{"element":"Mg","occu":1}],"abc":[0.254235999999999,0.745764,0.5],"properties":{"magmom":0.0},"label":"Mg","xyz":[2.1860279071199917,6.41239209288,4.2880205]},{"species":[{"element":"Mg","occu":1}],"abc":[0.7499500000000001,0.7499500000000001,0.0],"properties":{"magmom":0.0},"label":"Mg","xyz":[6.448385079000001,6.448385079000001,0.0]},{"species":[{"element":"Mg","occu":1}],"abc":[0.745764,0.745764,0.5],"properties":{"magmom":0.0},"label":"Mg","xyz":[6.41239209288,6.41239209288,4.2880205]},{"species":[{"element":"Zn","occu":1}],"abc":[0.0,0.0,0.0],"properties":{"magmom":0.0},"label":"Zn","xyz":[0.0,0.0,0.0]},{"species":[{"element":"Sn","occu":1}],"abc":[0.0,0.0,0.5],"properties":{"magmom":0.0},"label":"Sn","xyz":[0.0,0.0,4.2880205]},{"species":[{"element":"O","occu":1}],"abc":[0.0,0.258506,0.0],"properties":{"magmom":-0.0},"label":"O","xyz":[0.0,2.2227431605200003,0.0]},{"species":[{"element":"O","occu":1}],"abc":[0.0,0.269803,0.5],"properties":{"magmom":-0.0},"label":"O","xyz":[0.0,2.3198795112600004,4.2880205]},{"species":[{"element":"O","occu":1}],"abc":[0.5,0.251212,0.0],"properties":{"magmom":-0.0},"label":"O","xyz":[4.29921,2.1600262850400003,0.0]},{"species":[{"element":"O","occu":1}],"abc":[0.5,0.253204,0.5],"properties":{"magmom":-0.0},"label":"O","xyz":[4.29921,2.17715433768,4.2880205]},{"species":[{"element":"O","occu":1}],"abc":[0.0,0.741494,0.0],"properties":{"magmom":-0.0},"label":"O","xyz":[0.0,6.3756768394800005,0.0]},{"species":[{"element":"O","occu":1}],"abc":[0.0,0.730197,0.5],"properties":{"magmom":-0.0},"label":"O","xyz":[0.0,6.278540488740001,4.2880205]},{"species":[{"element":"O","occu":1}],"abc":[0.5,0.748788,0.0],"properties":{"magmom":-0.0},"label":"O","xyz":[4.29921,6.438393714960001,0.0]},{"species":[{"element":"O","occu":1}],"abc":[0.5,0.746796,0.5],"properties":{"magmom":-0.0},"label":"O","xyz":[4.29921,6.421265662320001,4.2880205]},{"species":[{"element":"O","occu":1}],"abc":[0.249238,0.249238,0.25035],"properties":{"magmom":-0.0},"label":"O","xyz":[2.14305300396,2.14305300396,2.14701186435]},{"species":[{"element":"O","occu":1}],"abc":[0.249238,0.249238,0.74965],"properties":{"magmom":-0.0},"label":"O","xyz":[2.14305300396,2.14305300396,6.4290291356500004]},{"species":[{"element":"O","occu":1}],"abc":[0.750761999999999,0.249238,0.25035],"properties":{"magmom":-0.0},"label":"O","xyz":[6.455366996039992,2.14305300396,2.14701186435]},{"species":[{"element":"O","occu":1}],"abc":[0.750761999999999,0.249238,0.74965],"properties":{"magmom":-0.0},"label":"O","xyz":[6.455366996039992,2.14305300396,6.4290291356500004]},{"species":[{"element":"O","occu":1}],"abc":[0.249238,0.750761999999999,0.25035],"properties":{"magmom":-0.0},"label":"O","xyz":[2.14305300396,6.455366996039992,2.14701186435]},{"species":[{"element":"O","occu":1}],"abc":[0.249238,0.750761999999999,0.74965],"properties":{"magmom":-0.0},"label":"O","xyz":[2.14305300396,6.455366996039992,6.4290291356500004]},{"species":[{"element":"O","occu":1}],"abc":[0.750761999999999,0.750761999999999,0.25035],"properties":{"magmom":-0.0},"label":"O","xyz":[6.455366996039992,6.455366996039992,2.14701186435]},{"species":[{"element":"O","occu":1}],"abc":[0.750761999999999,0.750761999999999,0.74965],"properties":{"magmom":-0.0},"label":"O","xyz":[6.455366996039992,6.455366996039992,6.4290291356500004]},{"species":[{"element":"O","occu":1}],"abc":[0.0,0.0,0.23103],"properties":{"magmom":-0.0},"label":"O","xyz":[0.0,0.0,1.98132275223]},{"species":[{"element":"O","occu":1}],"abc":[0.0,0.0,0.76897],"properties":{"magmom":-0.0},"label":"O","xyz":[0.0,0.0,6.59471824777]},{"species":[{"element":"O","occu":1}],"abc":[0.5,0.0,0.247575],"properties":{"magmom":-0.0},"label":"O","xyz":[4.29921,0.0,2.123213350575]},{"species":[{"element":"O","occu":1}],"abc":[0.5,0.0,0.752425],"properties":{"magmom":-0.0},"label":"O","xyz":[4.29921,0.0,6.452827649425]},{"species":[{"element":"O","occu":1}],"abc":[0.0,0.5,0.247575],"properties":{"magmom":-0.0},"label":"O","xyz":[0.0,4.29921,2.123213350575]},{"species":[{"element":"O","occu":1}],"abc":[0.0,0.5,0.752425],"properties":{"magmom":-0.0},"label":"O","xyz":[0.0,4.29921,6.452827649425]},{"species":[{"element":"O","occu":1}],"abc":[0.5,0.5,0.24954],"properties":{"magmom":-0.0},"label":"O","xyz":[4.29921,4.29921,2.14006527114]},{"species":[{"element":"O","occu":1}],"abc":[0.5,0.5,0.75046],"properties":{"magmom":-0.0},"label":"O","xyz":[4.29921,4.29921,6.43597572886]},{"species":[{"element":"O","occu":1}],"abc":[0.258506,0.0,0.0],"properties":{"magmom":-0.0},"label":"O","xyz":[2.2227431605200003,0.0,0.0]},{"species":[{"element":"O","occu":1}],"abc":[0.269803,0.0,0.5],"properties":{"magmom":-0.0},"label":"O","xyz":[2.3198795112600004,0.0,4.2880205]},{"species":[{"element":"O","occu":1}],"abc":[0.741494,0.0,0.0],"properties":{"magmom":-0.0},"label":"O","xyz":[6.3756768394800005,0.0,0.0]},{"species":[{"element":"O","occu":1}],"abc":[0.730197,0.0,0.5],"properties":{"magmom":-0.0},"label":"O","xyz":[6.278540488740001,0.0,4.2880205]},{"species":[{"element":"O","occu":1}],"abc":[0.251212,0.5,0.0],"properties":{"magmom":-0.0},"label":"O","xyz":[2.1600262850400003,4.29921,0.0]},{"species":[{"element":"O","occu":1}],"abc":[0.253204,0.5,0.5],"properties":{"magmom":-0.0},"label":"O","xyz":[2.17715433768,4.29921,4.2880205]},{"species":[{"element":"O","occu":1}],"abc":[0.748788,0.5,0.0],"properties":{"magmom":-0.0},"label":"O","xyz":[6.438393714960001,4.29921,0.0]},{"species":[{"element":"O","occu":1}],"abc":[0.746796,0.5,0.5],"properties":{"magmom":-0.0},"label":"O","xyz":[6.421265662320001,4.29921,4.2880205]}]}