{"@module":"pymatgen.core.structure","@class":"Structure","charge":0,"lattice":{"matrix":[[7.94834719,-0.0,0.0],[-0.0,3.94986172,0.0],[0.0,0.0,3.94986172]],"pbc":[true,true,true],"a":7.94834719,"b":3.94986172,"c":3.94986172,"alpha":90.0,"beta":90.0,"gamma":90.0,"volume":124.00540431410766},"properties":{},"sites":[{"species":[{"element":"Na","occu":1}],"abc":[0.0,-0.0,-0.0],"properties":{"magmom":-0.0},"label":"Na","xyz":[0.0,0.0,0.0]},{"species":[{"element":"Na","occu":1}],"abc":[0.5,-0.0,-0.0],"properties":{"magmom":-0.0},"label":"Na","xyz":[3.974173595,0.0,0.0]},{"species":[{"element":"Hf","occu":1}],"abc":[0.25163683,0.5,0.5],"properties":{"magmom":-0.0},"label":"Hf","xyz":[2.0000968906310073,1.97493086,1.97493086]},{"species":[{"element":"Hf","occu":1}],"abc":[0.74836417,0.5,0.5],"properties":{"magmom":-0.0},"label":"Hf","xyz":[5.948258247716182,1.97493086,1.97493086]},{"species":[{"element":"O","occu":1}],"abc":[0.19948253,0.5,0.0],"properties":{"magmom":0.0},"label":"O","xyz":[1.5855564067795906,1.97493086,0.0]},{"species":[{"element":"O","occu":1}],"abc":[0.80051647,0.5,0.0],"properties":{"magmom":0.0},"label":"O","xyz":[6.36278283487322,1.97493086,0.0]},{"species":[{"element":"O","occu":1}],"abc":[0.5,0.5,0.5],"properties":{"magmom":0.0},"label":"O","xyz":[3.974173595,1.97493086,1.97493086]},{"species":[{"element":"O","occu":1}],"abc":[0.19948253,-0.0,0.5],"properties":{"magmom":0.0},"label":"O","xyz":[1.5855564067795906,0.0,1.97493086]},{"species":[{"element":"O","occu":1}],"abc":[0.80051647,0.0,0.5],"properties":{"magmom":0.0},"label":"O","xyz":[6.36278283487322,0.0,1.97493086]}]}