{"@module":"pymatgen.core.structure","@class":"Structure","charge":0,"lattice":{"matrix":[[3.842492,0.0,0.0],[0.0,3.842492,0.0],[0.0,0.0,3.842492]],"pbc":[true,true,true],"a":3.842492,"b":3.842492,"c":3.842492,"alpha":90.0,"beta":90.0,"gamma":90.0,"volume":56.73341366101276},"properties":{},"sites":[{"species":[{"element":"Mg","occu":1}],"abc":[0.0,0.0,0.0],"properties":{"magmom":0.0},"label":"Mg","xyz":[0.0,0.0,0.0]},{"species":[{"element":"Ti","occu":1}],"abc":[0.5,0.5,0.5],"properties":{"magmom":-0.0},"label":"Ti","xyz":[1.921246,1.921246,1.921246]},{"species":[{"element":"O","occu":1}],"abc":[0.5,0.5,0.0],"properties":{"magmom":-0.0},"label":"O","xyz":[1.921246,1.921246,0.0]},{"species":[{"element":"O","occu":1}],"abc":[0.5,0.0,0.5],"properties":{"magmom":-0.0},"label":"O","xyz":[1.921246,0.0,1.921246]},{"species":[{"element":"O","occu":1}],"abc":[0.0,0.5,0.5],"properties":{"magmom":-0.0},"label":"O","xyz":[0.0,1.921246,1.921246]}]}