{"@module":"pymatgen.core.structure","@class":"Structure","charge":0,"lattice":{"matrix":[[4.349858,0.0,0.0],[0.0,8.558446,0.0],[0.0,0.0,9.032171]],"pbc":[true,true,true],"a":4.349858,"b":8.558446,"c":9.032171,"alpha":90.0,"beta":90.0,"gamma":90.0,"volume":336.2498859918743},"properties":{},"sites":[{"species":[{"element":"Mg","occu":1}],"abc":[0.0,0.5,0.0],"properties":{"magmom":0.0},"label":"Mg","xyz":[0.0,4.279223,0.0]},{"species":[{"element":"Mg","occu":1}],"abc":[0.0,0.5,0.5],"properties":{"magmom":0.0},"label":"Mg","xyz":[0.0,4.279223,4.5160855]},{"species":[{"element":"Mg","occu":1}],"abc":[0.5,0.0,0.240763999999999],"properties":{"magmom":0.0},"label":"Mg","xyz":[2.174929,0.0,2.174621618643991]},{"species":[{"element":"Mg","occu":1}],"abc":[0.5,0.0,0.759235999999999],"properties":{"magmom":0.0},"label":"Mg","xyz":[2.174929,0.0,6.857549381355991]},{"species":[{"element":"Mg","occu":1}],"abc":[0.5,0.5,0.248305],"properties":{"magmom":0.0},"label":"Mg","xyz":[2.174929,4.279223,2.242733220155]},{"species":[{"element":"Mg","occu":1}],"abc":[0.5,0.5,0.751695],"properties":{"magmom":0.0},"label":"Mg","xyz":[2.174929,4.279223,6.789437779845]},{"species":[{"element":"Mg","occu":1}],"abc":[0.5,0.252095,0.0],"properties":{"magmom":0.0},"label":"Mg","xyz":[2.174929,2.15754144437,0.0]},{"species":[{"element":"Mg","occu":1}],"abc":[0.5,0.26132299999999903,0.5],"properties":{"magmom":0.0},"label":"Mg","xyz":[2.174929,2.2365187840579916,4.5160855]},{"species":[{"element":"Mg","occu":1}],"abc":[0.5,0.747904999999999,0.0],"properties":{"magmom":0.0},"label":"Mg","xyz":[2.174929,6.4009045556299915,0.0]},{"species":[{"element":"Mg","occu":1}],"abc":[0.5,0.738676999999999,0.5],"properties":{"magmom":0.0},"label":"Mg","xyz":[2.174929,6.321927215941992,4.5160855]},{"species":[{"element":"Mg","occu":1}],"abc":[0.0,0.251305,0.245647999999999],"properties":{"magmom":0.0},"label":"Mg","xyz":[0.0,2.15078027203,2.218734741807991]},{"species":[{"element":"Mg","occu":1}],"abc":[0.0,0.251305,0.754351999999999],"properties":{"magmom":0.0},"label":"Mg","xyz":[0.0,2.15078027203,6.813436258191991]},{"species":[{"element":"Mg","occu":1}],"abc":[0.0,0.748695,0.245647999999999],"properties":{"magmom":0.0},"label":"Mg","xyz":[0.0,6.40766572797,2.218734741807991]},{"species":[{"element":"Mg","occu":1}],"abc":[0.0,0.748695,0.754351999999999],"properties":{"magmom":0.0},"label":"Mg","xyz":[0.0,6.40766572797,6.813436258191991]},{"species":[{"element":"Al","occu":1}],"abc":[0.0,0.0,0.0],"properties":{"magmom":0.0},"label":"Al","xyz":[0.0,0.0,0.0]},{"species":[{"element":"Bi","occu":1}],"abc":[0.0,0.0,0.5],"properties":{"magmom":-0.0},"label":"Bi","xyz":[0.0,0.0,4.5160855]},{"species":[{"element":"O","occu":1}],"abc":[0.0,0.248897999999999,0.0],"properties":{"magmom":-0.0},"label":"O","xyz":[0.0,2.1301800925079917,0.0]},{"species":[{"element":"O","occu":1}],"abc":[0.0,0.27486000000000005,0.5],"properties":{"magmom":-0.0},"label":"O","xyz":[0.0,2.3523744675600002,4.5160855]},{"species":[{"element":"O","occu":1}],"abc":[0.0,0.751101999999999,0.0],"properties":{"magmom":-0.0},"label":"O","xyz":[0.0,6.4282659074919914,0.0]},{"species":[{"element":"O","occu":1}],"abc":[0.0,0.72514,0.5],"properties":{"magmom":-0.0},"label":"O","xyz":[0.0,6.20607153244,4.5160855]},{"species":[{"element":"O","occu":1}],"abc":[0.5,0.249883,0.2509],"properties":{"magmom":-0.0},"label":"O","xyz":[2.174929,2.138610161818,2.2661717039]},{"species":[{"element":"O","occu":1}],"abc":[0.5,0.249883,0.7491],"properties":{"magmom":-0.0},"label":"O","xyz":[2.174929,2.138610161818,6.7659992960999995]},{"species":[{"element":"O","occu":1}],"abc":[0.5,0.750116999999999,0.2509],"properties":{"magmom":-0.0},"label":"O","xyz":[2.174929,6.419835838181991,2.2661717039]},{"species":[{"element":"O","occu":1}],"abc":[0.5,0.750116999999999,0.7491],"properties":{"magmom":-0.0},"label":"O","xyz":[2.174929,6.419835838181991,6.7659992960999995]},{"species":[{"element":"O","occu":1}],"abc":[0.5,0.0,0.0],"properties":{"magmom":-0.0},"label":"O","xyz":[2.174929,0.0,0.0]},{"species":[{"element":"O","occu":1}],"abc":[0.5,0.0,0.5],"properties":{"magmom":-0.0},"label":"O","xyz":[2.174929,0.0,4.5160855]},{"species":[{"element":"O","occu":1}],"abc":[0.5,0.5,0.0],"properties":{"magmom":-0.0},"label":"O","xyz":[2.174929,4.279223,0.0]},{"species":[{"element":"O","occu":1}],"abc":[0.5,0.5,0.5],"properties":{"magmom":-0.0},"label":"O","xyz":[2.174929,4.279223,4.5160855]},{"species":[{"element":"O","occu":1}],"abc":[0.0,0.0,0.193115999999999],"properties":{"magmom":-0.0},"label":"O","xyz":[0.0,0.0,1.744256734835991]},{"species":[{"element":"O","occu":1}],"abc":[0.0,0.0,0.806883999999999],"properties":{"magmom":-0.0},"label":"O","xyz":[0.0,0.0,7.287914265163991]},{"species":[{"element":"O","occu":1}],"abc":[0.0,0.5,0.243167],"properties":{"magmom":-0.0},"label":"O","xyz":[0.0,4.279223,2.196325925557]},{"species":[{"element":"O","occu":1}],"abc":[0.0,0.5,0.756833],"properties":{"magmom":-0.0},"label":"O","xyz":[0.0,4.279223,6.835845074443]}]}