{"@module":"pymatgen.core.structure","@class":"Structure","charge":0,"lattice":{"matrix":[[8.74298982,0.0,0.0],[-0.0,4.43004031,0.0],[0.0,0.0,4.43004031]],"pbc":[true,true,true],"a":8.74298982,"b":4.43004031,"c":4.43004031,"alpha":90.0,"beta":90.0,"gamma":90.0,"volume":171.5834234618125},"properties":{},"sites":[{"species":[{"element":"Ca","occu":1}],"abc":[0.0,0.0,0.0],"properties":{"magmom":-0.0},"label":"Ca","xyz":[0.0,0.0,0.0]},{"species":[{"element":"Mg","occu":1}],"abc":[0.0,0.5,0.5],"properties":{"magmom":-0.0},"label":"Mg","xyz":[0.0,2.215020155,2.215020155]},{"species":[{"element":"Mg","occu":1}],"abc":[0.5,0.5,0.5],"properties":{"magmom":-0.0},"label":"Mg","xyz":[4.37149491,2.215020155,2.215020155]},{"species":[{"element":"Mg","occu":1}],"abc":[0.25446435,-0.0,0.5],"properties":{"magmom":0.0},"label":"Mg","xyz":[2.224779221602917,0.0,2.215020155]},{"species":[{"element":"Mg","occu":1}],"abc":[0.74553565,0.0,0.5],"properties":{"magmom":-0.0},"label":"Mg","xyz":[6.518210598397083,0.0,2.215020155]},{"species":[{"element":"Mg","occu":1}],"abc":[0.25446435,0.5,-0.0],"properties":{"magmom":0.0},"label":"Mg","xyz":[2.224779221602917,2.215020155,0.0]},{"species":[{"element":"Mg","occu":1}],"abc":[0.74553565,0.5,0.0],"properties":{"magmom":0.0},"label":"Mg","xyz":[6.518210598397083,2.215020155,0.0]},{"species":[{"element":"Si","occu":1}],"abc":[0.5,0.0,0.0],"properties":{"magmom":0.0},"label":"Si","xyz":[4.37149491,0.0,0.0]},{"species":[{"element":"O","occu":1}],"abc":[0.25652778,0.0,-0.0],"properties":{"magmom":-0.0},"label":"O","xyz":[2.2428197690871996,0.0,0.0]},{"species":[{"element":"O","occu":1}],"abc":[0.74347222,0.0,0.0],"properties":{"magmom":-0.0},"label":"O","xyz":[6.500170050912801,0.0,0.0]},{"species":[{"element":"O","occu":1}],"abc":[0.25053406,0.5,0.5],"properties":{"magmom":-0.0},"label":"O","xyz":[2.1904167361432694,2.215020155,2.215020155]},{"species":[{"element":"O","occu":1}],"abc":[0.74946594,0.5,0.5],"properties":{"magmom":-0.0},"label":"O","xyz":[6.552573083856731,2.215020155,2.215020155]},{"species":[{"element":"O","occu":1}],"abc":[0.0,0.0,0.5],"properties":{"magmom":-0.0},"label":"O","xyz":[0.0,0.0,2.215020155]},{"species":[{"element":"O","occu":1}],"abc":[0.5,0.0,0.5],"properties":{"magmom":-0.0},"label":"O","xyz":[4.37149491,0.0,2.215020155]},{"species":[{"element":"O","occu":1}],"abc":[0.0,0.5,0.0],"properties":{"magmom":0.0},"label":"O","xyz":[0.0,2.215020155,0.0]},{"species":[{"element":"O","occu":1}],"abc":[0.5,0.5,0.0],"properties":{"magmom":-0.0},"label":"O","xyz":[4.37149491,2.215020155,0.0]}]}