{"@module":"pymatgen.core.structure","@class":"Structure","charge":0,"lattice":{"matrix":[[4.286092,0.0,0.0],[0.0,8.400672,0.0],[0.0,0.0,8.58108]],"pbc":[true,true,true],"a":4.286092,"b":8.400672,"c":8.58108,"alpha":90.0,"beta":90.0,"gamma":90.0,"volume":308.97082173910803},"properties":{},"sites":[{"species":[{"element":"Li","occu":1}],"abc":[0.0,0.0,0.008506],"properties":{"magmom":0.0},"label":"Li","xyz":[0.0,0.0,0.07299066648]},{"species":[{"element":"Mg","occu":1}],"abc":[0.0,0.5,0.0015300000000000001],"properties":{"magmom":0.0},"label":"Mg","xyz":[0.0,4.200336,0.0131290524]},{"species":[{"element":"Mg","occu":1}],"abc":[0.0,0.0,0.508737],"properties":{"magmom":0.0},"label":"Mg","xyz":[0.0,0.0,4.36551289596]},{"species":[{"element":"Mg","occu":1}],"abc":[0.5,0.756092,0.999949],"properties":{"magmom":0.0},"label":"Mg","xyz":[2.143046,6.351680893824,8.58064236492]},{"species":[{"element":"Mg","occu":1}],"abc":[0.5,0.24390799999999901,0.999949],"properties":{"magmom":0.0},"label":"Mg","xyz":[2.143046,2.0489911061759916,8.58064236492]},{"species":[{"element":"Mg","occu":1}],"abc":[0.5,0.73509,0.499239],"properties":{"magmom":0.0},"label":"Mg","xyz":[2.143046,6.17524998048,4.28400979812]},{"species":[{"element":"Mg","occu":1}],"abc":[0.5,0.26491000000000003,0.499239],"properties":{"magmom":0.0},"label":"Mg","xyz":[2.143046,2.2254220195200003,4.28400979812]},{"species":[{"element":"Mg","occu":1}],"abc":[0.5,0.0,0.7530800000000001],"properties":{"magmom":0.0},"label":"Mg","xyz":[2.143046,0.0,6.462239726400001]},{"species":[{"element":"Mg","occu":1}],"abc":[0.5,0.5,0.7451500000000001],"properties":{"magmom":0.0},"label":"Mg","xyz":[2.143046,4.200336,6.394191762000001]},{"species":[{"element":"Mg","occu":1}],"abc":[0.5,0.0,0.247324],"properties":{"magmom":0.0},"label":"Mg","xyz":[2.143046,0.0,2.12230702992]},{"species":[{"element":"Mg","occu":1}],"abc":[0.5,0.5,0.249156],"properties":{"magmom":0.0},"label":"Mg","xyz":[2.143046,4.200336,2.13802756848]},{"species":[{"element":"Mg","occu":1}],"abc":[0.0,0.735236999999999,0.756911],"properties":{"magmom":0.0},"label":"Mg","xyz":[0.0,6.176484879263992,6.4951138438800005]},{"species":[{"element":"Mg","occu":1}],"abc":[0.0,0.264762999999999,0.756911],"properties":{"magmom":0.0},"label":"Mg","xyz":[0.0,2.224187120735992,6.4951138438800005]},{"species":[{"element":"Mg","occu":1}],"abc":[0.0,0.757466,0.242365],"properties":{"magmom":0.0},"label":"Mg","xyz":[0.0,6.363223417152,2.0797534542]},{"species":[{"element":"Mg","occu":1}],"abc":[0.0,0.242534,0.242365],"properties":{"magmom":0.0},"label":"Mg","xyz":[0.0,2.037448582848,2.0797534542]},{"species":[{"element":"B","occu":1}],"abc":[0.0,0.5,0.440745],"properties":{"magmom":0.0},"label":"B","xyz":[0.0,4.200336,3.7820681046]},{"species":[{"element":"O","occu":1}],"abc":[0.0,0.5,0.772297999999999],"properties":{"magmom":-0.0},"label":"O","xyz":[0.0,4.200336,6.627150921839992]},{"species":[{"element":"O","occu":1}],"abc":[0.0,0.0,0.27309],"properties":{"magmom":-0.0},"label":"O","xyz":[0.0,0.0,2.3434071372]},{"species":[{"element":"O","occu":1}],"abc":[0.0,0.5,0.26756],"properties":{"magmom":-0.0},"label":"O","xyz":[0.0,4.200336,2.2959537648]},{"species":[{"element":"O","occu":1}],"abc":[0.5,0.748365,0.745846],"properties":{"magmom":-0.0},"label":"O","xyz":[2.143046,6.286768901279999,6.40016419368]},{"species":[{"element":"O","occu":1}],"abc":[0.5,0.251635,0.745846],"properties":{"magmom":-0.0},"label":"O","xyz":[2.143046,2.11390309872,6.40016419368]},{"species":[{"element":"O","occu":1}],"abc":[0.5,0.751219,0.252714],"properties":{"magmom":-0.0},"label":"O","xyz":[2.143046,6.3107444191679996,2.16855905112]},{"species":[{"element":"O","occu":1}],"abc":[0.5,0.248781,0.252714],"properties":{"magmom":-0.0},"label":"O","xyz":[2.143046,2.089927580832,2.16855905112]},{"species":[{"element":"O","occu":1}],"abc":[0.5,0.0,0.997896],"properties":{"magmom":-0.0},"label":"O","xyz":[2.143046,0.0,8.56302540768]},{"species":[{"element":"O","occu":1}],"abc":[0.5,0.5,0.010766],"properties":{"magmom":-0.0},"label":"O","xyz":[2.143046,4.200336,0.09238390728]},{"species":[{"element":"O","occu":1}],"abc":[0.5,0.0,0.49979],"properties":{"magmom":-0.0},"label":"O","xyz":[2.143046,0.0,4.2887379732]},{"species":[{"element":"O","occu":1}],"abc":[0.5,0.5,0.487560999999999],"properties":{"magmom":-0.0},"label":"O","xyz":[2.143046,4.200336,4.183799945879992]},{"species":[{"element":"O","occu":1}],"abc":[0.0,0.746454,0.005000999999999],"properties":{"magmom":-0.0},"label":"O","xyz":[0.0,6.270715217088,0.04291398107999142]},{"species":[{"element":"O","occu":1}],"abc":[0.0,0.253546,0.005000999999999],"properties":{"magmom":-0.0},"label":"O","xyz":[0.0,2.129956782912,0.04291398107999142]},{"species":[{"element":"O","occu":1}],"abc":[0.0,0.670841999999999,0.491382],"properties":{"magmom":-0.0},"label":"O","xyz":[0.0,5.635523605823992,4.21658825256]},{"species":[{"element":"O","occu":1}],"abc":[0.0,0.329158,0.491382],"properties":{"magmom":-0.0},"label":"O","xyz":[0.0,2.7651483941760002,4.21658825256]}]}