{"@module":"pymatgen.core.structure","@class":"Structure","charge":0,"lattice":{"matrix":[[8.610962,0.0,0.0],[0.0,8.610962,0.0],[0.0,0.0,8.609807]],"pbc":[true,true,true],"a":8.610962,"b":8.610962,"c":8.609807,"alpha":90.0,"beta":90.0,"gamma":90.0,"volume":638.4057084358259},"properties":{},"sites":[{"species":[{"element":"Li","occu":1}],"abc":[0.0,0.0,0.0],"properties":{"magmom":0.0},"label":"Li","xyz":[0.0,0.0,0.0]},{"species":[{"element":"La","occu":1}],"abc":[0.5,0.5,0.0],"properties":{"magmom":-0.0},"label":"La","xyz":[4.305481,4.305481,0.0]},{"species":[{"element":"Mg","occu":1}],"abc":[0.5,0.0,0.0],"properties":{"magmom":0.0},"label":"Mg","xyz":[4.305481,0.0,0.0]},{"species":[{"element":"Mg","occu":1}],"abc":[0.0,0.5,0.0],"properties":{"magmom":0.0},"label":"Mg","xyz":[0.0,4.305481,0.0]},{"species":[{"element":"Mg","occu":1}],"abc":[0.0,0.0,0.5],"properties":{"magmom":0.0},"label":"Mg","xyz":[0.0,0.0,4.3049035]},{"species":[{"element":"Mg","occu":1}],"abc":[0.5,0.0,0.5],"properties":{"magmom":0.0},"label":"Mg","xyz":[4.305481,0.0,4.3049035]},{"species":[{"element":"Mg","occu":1}],"abc":[0.0,0.5,0.5],"properties":{"magmom":0.0},"label":"Mg","xyz":[0.0,4.305481,4.3049035]},{"species":[{"element":"Mg","occu":1}],"abc":[0.5,0.5,0.5],"properties":{"magmom":0.0},"label":"Mg","xyz":[4.305481,4.305481,4.3049035]},{"species":[{"element":"Mg","occu":1}],"abc":[0.23791299999999901,0.23791299999999901,0.0],"properties":{"magmom":0.0},"label":"Mg","xyz":[2.0486598023059917,2.0486598023059917,0.0]},{"species":[{"element":"Mg","occu":1}],"abc":[0.762087,0.23791299999999901,0.0],"properties":{"magmom":0.0},"label":"Mg","xyz":[6.562302197694001,2.0486598023059917,0.0]},{"species":[{"element":"Mg","occu":1}],"abc":[0.23791299999999901,0.762087,0.0],"properties":{"magmom":0.0},"label":"Mg","xyz":[2.0486598023059917,6.562302197694001,0.0]},{"species":[{"element":"Mg","occu":1}],"abc":[0.762087,0.762087,0.0],"properties":{"magmom":0.0},"label":"Mg","xyz":[6.562302197694001,6.562302197694001,0.0]},{"species":[{"element":"Mg","occu":1}],"abc":[0.247986999999999,0.247986999999999,0.5],"properties":{"magmom":0.0},"label":"Mg","xyz":[2.1354066334939916,2.1354066334939916,4.3049035]},{"species":[{"element":"Mg","occu":1}],"abc":[0.752012999999999,0.247986999999999,0.5],"properties":{"magmom":0.0},"label":"Mg","xyz":[6.475555366505993,2.1354066334939916,4.3049035]},{"species":[{"element":"Mg","occu":1}],"abc":[0.247986999999999,0.752012999999999,0.5],"properties":{"magmom":0.0},"label":"Mg","xyz":[2.1354066334939916,6.475555366505993,4.3049035]},{"species":[{"element":"Mg","occu":1}],"abc":[0.752012999999999,0.752012999999999,0.5],"properties":{"magmom":0.0},"label":"Mg","xyz":[6.475555366505993,6.475555366505993,4.3049035]},{"species":[{"element":"Mg","occu":1}],"abc":[0.245447,0.0,0.247596999999999],"properties":{"magmom":0.0},"label":"Mg","xyz":[2.113534790014,0.0,2.1317623837789914]},{"species":[{"element":"Mg","occu":1}],"abc":[0.754552999999999,0.0,0.247596999999999],"properties":{"magmom":0.0},"label":"Mg","xyz":[6.497427209985992,0.0,2.1317623837789914]},{"species":[{"element":"Mg","occu":1}],"abc":[0.240406999999999,0.5,0.257874999999999],"properties":{"magmom":0.0},"label":"Mg","xyz":[2.0701355415339915,4.305481,2.2202539801249914]},{"species":[{"element":"Mg","occu":1}],"abc":[0.759593,0.5,0.257874999999999],"properties":{"magmom":0.0},"label":"Mg","xyz":[6.540826458466,4.305481,2.2202539801249914]},{"species":[{"element":"Mg","occu":1}],"abc":[0.245447,0.0,0.752402999999999],"properties":{"magmom":0.0},"label":"Mg","xyz":[2.113534790014,0.0,6.478044616220992]},{"species":[{"element":"Mg","occu":1}],"abc":[0.754552999999999,0.0,0.752402999999999],"properties":{"magmom":0.0},"label":"Mg","xyz":[6.497427209985992,0.0,6.478044616220992]},{"species":[{"element":"Mg","occu":1}],"abc":[0.240406999999999,0.5,0.742124999999999],"properties":{"magmom":0.0},"label":"Mg","xyz":[2.0701355415339915,4.305481,6.389553019874992]},{"species":[{"element":"Mg","occu":1}],"abc":[0.759593,0.5,0.742124999999999],"properties":{"magmom":0.0},"label":"Mg","xyz":[6.540826458466,4.305481,6.389553019874992]},{"species":[{"element":"Mg","occu":1}],"abc":[0.0,0.245447,0.247596999999999],"properties":{"magmom":0.0},"label":"Mg","xyz":[0.0,2.113534790014,2.1317623837789914]},{"species":[{"element":"Mg","occu":1}],"abc":[0.5,0.240406999999999,0.257874999999999],"properties":{"magmom":0.0},"label":"Mg","xyz":[4.305481,2.0701355415339915,2.2202539801249914]},{"species":[{"element":"Mg","occu":1}],"abc":[0.0,0.754552999999999,0.247596999999999],"properties":{"magmom":0.0},"label":"Mg","xyz":[0.0,6.497427209985992,2.1317623837789914]},{"species":[{"element":"Mg","occu":1}],"abc":[0.5,0.759593,0.257874999999999],"properties":{"magmom":0.0},"label":"Mg","xyz":[4.305481,6.540826458466,2.2202539801249914]},{"species":[{"element":"Mg","occu":1}],"abc":[0.0,0.245447,0.752402999999999],"properties":{"magmom":0.0},"label":"Mg","xyz":[0.0,2.113534790014,6.478044616220992]},{"species":[{"element":"Mg","occu":1}],"abc":[0.5,0.240406999999999,0.742124999999999],"properties":{"magmom":0.0},"label":"Mg","xyz":[4.305481,2.0701355415339915,6.389553019874992]},{"species":[{"element":"Mg","occu":1}],"abc":[0.0,0.754552999999999,0.752402999999999],"properties":{"magmom":0.0},"label":"Mg","xyz":[0.0,6.497427209985992,6.478044616220992]},{"species":[{"element":"Mg","occu":1}],"abc":[0.5,0.759593,0.742124999999999],"properties":{"magmom":0.0},"label":"Mg","xyz":[4.305481,6.540826458466,6.389553019874992]},{"species":[{"element":"O","occu":1}],"abc":[0.0,0.0,0.257495],"properties":{"magmom":-0.0},"label":"O","xyz":[0.0,0.0,2.216982253465]},{"species":[{"element":"O","occu":1}],"abc":[0.5,0.0,0.25431000000000004],"properties":{"magmom":-0.0},"label":"O","xyz":[4.305481,0.0,2.1895600181700003]},{"species":[{"element":"O","occu":1}],"abc":[0.0,0.5,0.25431000000000004],"properties":{"magmom":-0.0},"label":"O","xyz":[0.0,4.305481,2.1895600181700003]},{"species":[{"element":"O","occu":1}],"abc":[0.5,0.5,0.268495],"properties":{"magmom":-0.0},"label":"O","xyz":[4.305481,4.305481,2.3116901304649997]},{"species":[{"element":"O","occu":1}],"abc":[0.0,0.0,0.742505],"properties":{"magmom":-0.0},"label":"O","xyz":[0.0,0.0,6.392824746535]},{"species":[{"element":"O","occu":1}],"abc":[0.5,0.0,0.7456900000000001],"properties":{"magmom":-0.0},"label":"O","xyz":[4.305481,0.0,6.420246981830001]},{"species":[{"element":"O","occu":1}],"abc":[0.0,0.5,0.7456900000000001],"properties":{"magmom":-0.0},"label":"O","xyz":[0.0,4.305481,6.420246981830001]},{"species":[{"element":"O","occu":1}],"abc":[0.5,0.5,0.731505],"properties":{"magmom":-0.0},"label":"O","xyz":[4.305481,4.305481,6.298116869535]},{"species":[{"element":"O","occu":1}],"abc":[0.251133999999999,0.251133999999999,0.24913000000000002],"properties":{"magmom":-0.0},"label":"O","xyz":[2.1625053309079916,2.1625053309079916,2.14496121791]},{"species":[{"element":"O","occu":1}],"abc":[0.748865999999999,0.251133999999999,0.24913000000000002],"properties":{"magmom":-0.0},"label":"O","xyz":[6.448456669091992,2.1625053309079916,2.14496121791]},{"species":[{"element":"O","occu":1}],"abc":[0.251133999999999,0.748865999999999,0.24913000000000002],"properties":{"magmom":-0.0},"label":"O","xyz":[2.1625053309079916,6.448456669091992,2.14496121791]},{"species":[{"element":"O","occu":1}],"abc":[0.748865999999999,0.748865999999999,0.24913000000000002],"properties":{"magmom":-0.0},"label":"O","xyz":[6.448456669091992,6.448456669091992,2.14496121791]},{"species":[{"element":"O","occu":1}],"abc":[0.251133999999999,0.251133999999999,0.75087],"properties":{"magmom":-0.0},"label":"O","xyz":[2.1625053309079916,2.1625053309079916,6.46484578209]},{"species":[{"element":"O","occu":1}],"abc":[0.748865999999999,0.251133999999999,0.75087],"properties":{"magmom":-0.0},"label":"O","xyz":[6.448456669091992,2.1625053309079916,6.46484578209]},{"species":[{"element":"O","occu":1}],"abc":[0.251133999999999,0.748865999999999,0.75087],"properties":{"magmom":-0.0},"label":"O","xyz":[2.1625053309079916,6.448456669091992,6.46484578209]},{"species":[{"element":"O","occu":1}],"abc":[0.748865999999999,0.748865999999999,0.75087],"properties":{"magmom":-0.0},"label":"O","xyz":[6.448456669091992,6.448456669091992,6.46484578209]},{"species":[{"element":"O","occu":1}],"abc":[0.253784,0.0,0.0],"properties":{"magmom":-0.0},"label":"O","xyz":[2.1853243802080002,0.0,0.0]},{"species":[{"element":"O","occu":1}],"abc":[0.746216,0.0,0.0],"properties":{"magmom":-0.0},"label":"O","xyz":[6.425637619792,0.0,0.0]},{"species":[{"element":"O","occu":1}],"abc":[0.232646,0.5,0.0],"properties":{"magmom":-0.0},"label":"O","xyz":[2.003305865452,4.305481,0.0]},{"species":[{"element":"O","occu":1}],"abc":[0.767354,0.5,0.0],"properties":{"magmom":-0.0},"label":"O","xyz":[6.607656134548001,4.305481,0.0]},{"species":[{"element":"O","occu":1}],"abc":[0.250905,0.0,0.5],"properties":{"magmom":-0.0},"label":"O","xyz":[2.16053342061,0.0,4.3049035]},{"species":[{"element":"O","occu":1}],"abc":[0.749095,0.0,0.5],"properties":{"magmom":-0.0},"label":"O","xyz":[6.4504285793900005,0.0,4.3049035]},{"species":[{"element":"O","occu":1}],"abc":[0.247513999999999,0.5,0.5],"properties":{"magmom":-0.0},"label":"O","xyz":[2.1313336484679914,4.305481,4.3049035]},{"species":[{"element":"O","occu":1}],"abc":[0.752486,0.5,0.5],"properties":{"magmom":-0.0},"label":"O","xyz":[6.479628351532001,4.305481,4.3049035]},{"species":[{"element":"O","occu":1}],"abc":[0.0,0.253784,0.0],"properties":{"magmom":-0.0},"label":"O","xyz":[0.0,2.1853243802080002,0.0]},{"species":[{"element":"O","occu":1}],"abc":[0.5,0.232646,0.0],"properties":{"magmom":-0.0},"label":"O","xyz":[4.305481,2.003305865452,0.0]},{"species":[{"element":"O","occu":1}],"abc":[0.0,0.746216,0.0],"properties":{"magmom":-0.0},"label":"O","xyz":[0.0,6.425637619792,0.0]},{"species":[{"element":"O","occu":1}],"abc":[0.5,0.767354,0.0],"properties":{"magmom":-0.0},"label":"O","xyz":[4.305481,6.607656134548001,0.0]},{"species":[{"element":"O","occu":1}],"abc":[0.0,0.250905,0.5],"properties":{"magmom":-0.0},"label":"O","xyz":[0.0,2.16053342061,4.3049035]},{"species":[{"element":"O","occu":1}],"abc":[0.5,0.247513999999999,0.5],"properties":{"magmom":-0.0},"label":"O","xyz":[4.305481,2.1313336484679914,4.3049035]},{"species":[{"element":"O","occu":1}],"abc":[0.0,0.749095,0.5],"properties":{"magmom":-0.0},"label":"O","xyz":[0.0,6.4504285793900005,4.3049035]},{"species":[{"element":"O","occu":1}],"abc":[0.5,0.752486,0.5],"properties":{"magmom":-0.0},"label":"O","xyz":[4.305481,6.479628351532001,4.3049035]}]}