{"@module":"pymatgen.core.structure","@class":"Structure","charge":0,"lattice":{"matrix":[[8.414847,0.0,0.0],[0.0,8.595044,0.0],[0.0,0.0,8.842103999999999]],"pbc":[true,true,true],"a":8.414847,"b":8.595044,"c":8.842103999999999,"alpha":90.0,"beta":90.0,"gamma":90.0,"volume":639.5138389918683},"properties":{},"sites":[{"species":[{"element":"Rb","occu":1}],"abc":[0.0,0.980451,0.0],"properties":{"magmom":-0.0},"label":"Rb","xyz":[0.0,8.427019484844,0.0]},{"species":[{"element":"Mg","occu":1}],"abc":[0.0,0.001428,0.5],"properties":{"magmom":0.0},"label":"Mg","xyz":[0.0,0.012273722832,4.4210519999999995]},{"species":[{"element":"Mg","occu":1}],"abc":[0.5,0.996657999999999,0.5],"properties":{"magmom":0.0},"label":"Mg","xyz":[4.2074235,8.566319362951992,4.4210519999999995]},{"species":[{"element":"Mg","occu":1}],"abc":[0.0,0.508632,0.0],"properties":{"magmom":0.0},"label":"Mg","xyz":[0.0,4.371714419808,0.0]},{"species":[{"element":"Mg","occu":1}],"abc":[0.5,0.492368,0.0],"properties":{"magmom":0.0},"label":"Mg","xyz":[4.2074235,4.231924624192,0.0]},{"species":[{"element":"Mg","occu":1}],"abc":[0.0,0.497948,0.5],"properties":{"magmom":0.0},"label":"Mg","xyz":[0.0,4.279884969712,4.4210519999999995]},{"species":[{"element":"Mg","occu":1}],"abc":[0.5,0.501545999999999,0.5],"properties":{"magmom":0.0},"label":"Mg","xyz":[4.2074235,4.310809938023992,4.4210519999999995]},{"species":[{"element":"Mg","occu":1}],"abc":[0.257515999999999,0.00042,0.264478],"properties":{"magmom":0.0},"label":"Mg","xyz":[2.1669577400519917,0.00360991848,2.338541981712]},{"species":[{"element":"Mg","occu":1}],"abc":[0.742483999999999,0.00042,0.264478],"properties":{"magmom":0.0},"label":"Mg","xyz":[6.247889259947992,0.00360991848,2.338541981712]},{"species":[{"element":"Mg","occu":1}],"abc":[0.257515999999999,0.00042,0.735522],"properties":{"magmom":0.0},"label":"Mg","xyz":[2.1669577400519917,0.00360991848,6.503562018287999]},{"species":[{"element":"Mg","occu":1}],"abc":[0.742483999999999,0.00042,0.735522],"properties":{"magmom":0.0},"label":"Mg","xyz":[6.247889259947992,0.00360991848,6.503562018287999]},{"species":[{"element":"Mg","occu":1}],"abc":[0.2505,0.498739,0.250231],"properties":{"magmom":0.0},"label":"Mg","xyz":[2.1079191735,4.286683649516,2.2125685260239996]},{"species":[{"element":"Mg","occu":1}],"abc":[0.7495,0.498739,0.250231],"properties":{"magmom":0.0},"label":"Mg","xyz":[6.306927826500001,4.286683649516,2.2125685260239996]},{"species":[{"element":"Mg","occu":1}],"abc":[0.2505,0.498739,0.749769],"properties":{"magmom":0.0},"label":"Mg","xyz":[2.1079191735,4.286683649516,6.6295354739759995]},{"species":[{"element":"Mg","occu":1}],"abc":[0.7495,0.498739,0.749769],"properties":{"magmom":0.0},"label":"Mg","xyz":[6.306927826500001,4.286683649516,6.6295354739759995]},{"species":[{"element":"Mg","occu":1}],"abc":[0.267787,0.737510999999999,0.0],"properties":{"magmom":0.0},"label":"Mg","xyz":[2.253386633589,6.3389394954839915,0.0]},{"species":[{"element":"Mg","occu":1}],"abc":[0.732213,0.737510999999999,0.0],"properties":{"magmom":0.0},"label":"Mg","xyz":[6.161460366411,6.3389394954839915,0.0]},{"species":[{"element":"Mg","occu":1}],"abc":[0.25316,0.747935,0.5],"properties":{"magmom":0.0},"label":"Mg","xyz":[2.13030266652,6.42853423414,4.4210519999999995]},{"species":[{"element":"Mg","occu":1}],"abc":[0.7468400000000001,0.747935,0.5],"properties":{"magmom":0.0},"label":"Mg","xyz":[6.28454433348,6.42853423414,4.4210519999999995]},{"species":[{"element":"Mg","occu":1}],"abc":[0.24506399999999903,0.256078,0.0],"properties":{"magmom":0.0},"label":"Mg","xyz":[2.062176065207992,2.2010016774319996,0.0]},{"species":[{"element":"Mg","occu":1}],"abc":[0.754935999999999,0.256078,0.0],"properties":{"magmom":0.0},"label":"Mg","xyz":[6.352670934791992,2.2010016774319996,0.0]},{"species":[{"element":"Mg","occu":1}],"abc":[0.248334,0.251452,0.5],"properties":{"magmom":0.0},"label":"Mg","xyz":[2.089692614898,2.161241003888,4.4210519999999995]},{"species":[{"element":"Mg","occu":1}],"abc":[0.751666,0.251452,0.5],"properties":{"magmom":0.0},"label":"Mg","xyz":[6.325154385102,2.161241003888,4.4210519999999995]},{"species":[{"element":"Mg","occu":1}],"abc":[0.0,0.746051,0.263169],"properties":{"magmom":0.0},"label":"Mg","xyz":[0.0,6.412341171244,2.3269676675759996]},{"species":[{"element":"Mg","occu":1}],"abc":[0.5,0.754734999999999,0.243696],"properties":{"magmom":0.0},"label":"Mg","xyz":[4.2074235,6.486980533339992,2.154785376384]},{"species":[{"element":"Mg","occu":1}],"abc":[0.0,0.746051,0.736831],"properties":{"magmom":0.0},"label":"Mg","xyz":[0.0,6.412341171244,6.5151363324239995]},{"species":[{"element":"Mg","occu":1}],"abc":[0.5,0.754734999999999,0.756304],"properties":{"magmom":0.0},"label":"Mg","xyz":[4.2074235,6.486980533339992,6.687318623615999]},{"species":[{"element":"Mg","occu":1}],"abc":[0.0,0.250615,0.253478],"properties":{"magmom":0.0},"label":"Mg","xyz":[0.0,2.15404695206,2.2412788377119996]},{"species":[{"element":"Mg","occu":1}],"abc":[0.5,0.247719,0.263841],"properties":{"magmom":0.0},"label":"Mg","xyz":[4.2074235,2.1291557046359997,2.3329095614639996]},{"species":[{"element":"Mg","occu":1}],"abc":[0.0,0.250615,0.746522],"properties":{"magmom":0.0},"label":"Mg","xyz":[0.0,2.15404695206,6.600825162287999]},{"species":[{"element":"Mg","occu":1}],"abc":[0.5,0.247719,0.736159],"properties":{"magmom":0.0},"label":"Mg","xyz":[4.2074235,2.1291557046359997,6.509194438535999]},{"species":[{"element":"B","occu":1}],"abc":[0.5,0.066635,0.0],"properties":{"magmom":0.0},"label":"B","xyz":[4.2074235,0.57273075694,0.0]},{"species":[{"element":"O","occu":1}],"abc":[0.5,0.722135,0.0],"properties":{"magmom":-0.0},"label":"O","xyz":[4.2074235,6.20678209894,0.0]},{"species":[{"element":"O","occu":1}],"abc":[0.0,0.744201,0.5],"properties":{"magmom":-0.0},"label":"O","xyz":[0.0,6.396440339844,4.4210519999999995]},{"species":[{"element":"O","occu":1}],"abc":[0.5,0.745093999999999,0.5],"properties":{"magmom":-0.0},"label":"O","xyz":[4.2074235,6.404115714135991,4.4210519999999995]},{"species":[{"element":"O","occu":1}],"abc":[0.0,0.271731,0.0],"properties":{"magmom":-0.0},"label":"O","xyz":[0.0,2.335539901164,0.0]},{"species":[{"element":"O","occu":1}],"abc":[0.5,0.23669,0.0],"properties":{"magmom":-0.0},"label":"O","xyz":[4.2074235,2.0343609643600002,0.0]},{"species":[{"element":"O","occu":1}],"abc":[0.0,0.254266999999999,0.5],"properties":{"magmom":-0.0},"label":"O","xyz":[0.0,2.1854360527479915,4.4210519999999995]},{"species":[{"element":"O","occu":1}],"abc":[0.5,0.254947,0.5],"properties":{"magmom":-0.0},"label":"O","xyz":[4.2074235,2.191280682668,4.4210519999999995]},{"species":[{"element":"O","occu":1}],"abc":[0.251403,0.752751,0.24804],"properties":{"magmom":-0.0},"label":"O","xyz":[2.115517780341,6.469927966044,2.1931954761599997]},{"species":[{"element":"O","occu":1}],"abc":[0.748597,0.752751,0.24804],"properties":{"magmom":-0.0},"label":"O","xyz":[6.299329219659,6.469927966044,2.1931954761599997]},{"species":[{"element":"O","occu":1}],"abc":[0.251403,0.752751,0.7519600000000001],"properties":{"magmom":-0.0},"label":"O","xyz":[2.115517780341,6.469927966044,6.64890852384]},{"species":[{"element":"O","occu":1}],"abc":[0.748597,0.752751,0.7519600000000001],"properties":{"magmom":-0.0},"label":"O","xyz":[6.299329219659,6.469927966044,6.64890852384]},{"species":[{"element":"O","occu":1}],"abc":[0.250009,0.247115,0.248094999999999],"properties":{"magmom":-0.0},"label":"O","xyz":[2.103787483623,2.1239642980599998,2.193681791879991]},{"species":[{"element":"O","occu":1}],"abc":[0.749991,0.247115,0.248094999999999],"properties":{"magmom":-0.0},"label":"O","xyz":[6.311059516377,2.1239642980599998,2.193681791879991]},{"species":[{"element":"O","occu":1}],"abc":[0.250009,0.247115,0.751904999999999],"properties":{"magmom":-0.0},"label":"O","xyz":[2.103787483623,2.1239642980599998,6.648422208119991]},{"species":[{"element":"O","occu":1}],"abc":[0.749991,0.247115,0.751904999999999],"properties":{"magmom":-0.0},"label":"O","xyz":[6.311059516377,2.1239642980599998,6.648422208119991]},{"species":[{"element":"O","occu":1}],"abc":[0.340049,0.009769,0.0],"properties":{"magmom":-0.0},"label":"O","xyz":[2.861460307503,0.083964984836,0.0]},{"species":[{"element":"O","occu":1}],"abc":[0.659951,0.009769,0.0],"properties":{"magmom":-0.0},"label":"O","xyz":[5.553386692497,0.083964984836,0.0]},{"species":[{"element":"O","occu":1}],"abc":[0.250996999999999,0.999772,0.5],"properties":{"magmom":-0.0},"label":"O","xyz":[2.1121013524589918,8.593084329967999,4.4210519999999995]},{"species":[{"element":"O","occu":1}],"abc":[0.749003,0.999772,0.5],"properties":{"magmom":-0.0},"label":"O","xyz":[6.302745647541,8.593084329967999,4.4210519999999995]},{"species":[{"element":"O","occu":1}],"abc":[0.255312,0.492618,0.0],"properties":{"magmom":-0.0},"label":"O","xyz":[2.1484114172639996,4.234073385192,0.0]},{"species":[{"element":"O","occu":1}],"abc":[0.744688,0.492618,0.0],"properties":{"magmom":-0.0},"label":"O","xyz":[6.266435582736,4.234073385192,0.0]},{"species":[{"element":"O","occu":1}],"abc":[0.251123,0.499697,0.5],"properties":{"magmom":-0.0},"label":"O","xyz":[2.113161623181,4.294917701668,4.4210519999999995]},{"species":[{"element":"O","occu":1}],"abc":[0.748877,0.499697,0.5],"properties":{"magmom":-0.0},"label":"O","xyz":[6.301685376819,4.294917701668,4.4210519999999995]},{"species":[{"element":"O","occu":1}],"abc":[0.0,0.000509,0.276144],"properties":{"magmom":-0.0},"label":"O","xyz":[0.0,0.004374877396,2.4416939669759996]},{"species":[{"element":"O","occu":1}],"abc":[0.5,0.003065999999999,0.273741],"properties":{"magmom":-0.0},"label":"O","xyz":[4.2074235,0.026352404903991405,2.420446391064]},{"species":[{"element":"O","occu":1}],"abc":[0.0,0.000509,0.7238559999999991],"properties":{"magmom":-0.0},"label":"O","xyz":[0.0,0.004374877396,6.400410033023991]},{"species":[{"element":"O","occu":1}],"abc":[0.5,0.003065999999999,0.726259],"properties":{"magmom":-0.0},"label":"O","xyz":[4.2074235,0.026352404903991405,6.421657608935999]},{"species":[{"element":"O","occu":1}],"abc":[0.0,0.498613,0.257463999999999],"properties":{"magmom":-0.0},"label":"O","xyz":[0.0,4.285600673972,2.276523464255991]},{"species":[{"element":"O","occu":1}],"abc":[0.5,0.493444999999999,0.25055499999999903],"properties":{"magmom":-0.0},"label":"O","xyz":[4.2074235,4.2411814865799915,2.2154333677199913]},{"species":[{"element":"O","occu":1}],"abc":[0.0,0.498613,0.742536],"properties":{"magmom":-0.0},"label":"O","xyz":[0.0,4.285600673972,6.565580535743999]},{"species":[{"element":"O","occu":1}],"abc":[0.5,0.493444999999999,0.749444999999999],"properties":{"magmom":-0.0},"label":"O","xyz":[4.2074235,4.2411814865799915,6.626670632279991]}]}