{"@module":"pymatgen.core.structure","@class":"Structure","charge":0,"lattice":{"matrix":[[8.709009,0.0,0.0],[0.0,8.709009,0.0],[0.0,0.0,8.719804]],"pbc":[true,true,true],"a":8.709009,"b":8.709009,"c":8.719804,"alpha":90.0,"beta":90.0,"gamma":90.0,"volume":661.3695593051449},"properties":{},"sites":[{"species":[{"element":"Mg","occu":1}],"abc":[0.0,0.5,0.0],"properties":{"magmom":0.002},"label":"Mg","xyz":[0.0,4.3545045,0.0]},{"species":[{"element":"Mg","occu":1}],"abc":[0.5,0.0,0.0],"properties":{"magmom":0.002},"label":"Mg","xyz":[4.3545045,0.0,0.0]},{"species":[{"element":"Mg","occu":1}],"abc":[0.0,0.0,0.5],"properties":{"magmom":0.001},"label":"Mg","xyz":[0.0,0.0,4.359902]},{"species":[{"element":"Mg","occu":1}],"abc":[0.0,0.5,0.5],"properties":{"magmom":0.001},"label":"Mg","xyz":[0.0,4.3545045,4.359902]},{"species":[{"element":"Mg","occu":1}],"abc":[0.5,0.0,0.5],"properties":{"magmom":0.001},"label":"Mg","xyz":[4.3545045,0.0,4.359902]},{"species":[{"element":"Mg","occu":1}],"abc":[0.5,0.5,0.5],"properties":{"magmom":0.006},"label":"Mg","xyz":[4.3545045,4.3545045,4.359902]},{"species":[{"element":"Mg","occu":1}],"abc":[0.247121999999999,0.247121999999999,0.0],"properties":{"magmom":0.002},"label":"Mg","xyz":[2.1521877220979913,2.1521877220979913,0.0]},{"species":[{"element":"Mg","occu":1}],"abc":[0.247121999999999,0.752877999999999,0.0],"properties":{"magmom":0.002},"label":"Mg","xyz":[2.1521877220979913,6.556821277901991,0.0]},{"species":[{"element":"Mg","occu":1}],"abc":[0.752877999999999,0.247121999999999,0.0],"properties":{"magmom":0.002},"label":"Mg","xyz":[6.556821277901991,2.1521877220979913,0.0]},{"species":[{"element":"Mg","occu":1}],"abc":[0.752877999999999,0.752877999999999,0.0],"properties":{"magmom":0.002},"label":"Mg","xyz":[6.556821277901991,6.556821277901991,0.0]},{"species":[{"element":"Mg","occu":1}],"abc":[0.249461,0.249461,0.5],"properties":{"magmom":0.002},"label":"Mg","xyz":[2.1725580941489997,2.1725580941489997,4.359902]},{"species":[{"element":"Mg","occu":1}],"abc":[0.249461,0.750539,0.5],"properties":{"magmom":0.002},"label":"Mg","xyz":[2.1725580941489997,6.536450905851,4.359902]},{"species":[{"element":"Mg","occu":1}],"abc":[0.750539,0.249461,0.5],"properties":{"magmom":0.002},"label":"Mg","xyz":[6.536450905851,2.1725580941489997,4.359902]},{"species":[{"element":"Mg","occu":1}],"abc":[0.750539,0.750539,0.5],"properties":{"magmom":0.002},"label":"Mg","xyz":[6.536450905851,6.536450905851,4.359902]},{"species":[{"element":"Mg","occu":1}],"abc":[0.0,0.253425,0.255562],"properties":{"magmom":0.002},"label":"Mg","xyz":[0.0,2.2070806058250003,2.228450549848]},{"species":[{"element":"Mg","occu":1}],"abc":[0.0,0.746575,0.255562],"properties":{"magmom":0.002},"label":"Mg","xyz":[0.0,6.501928394175,2.228450549848]},{"species":[{"element":"Mg","occu":1}],"abc":[0.5,0.243535,0.257605],"properties":{"magmom":0.003},"label":"Mg","xyz":[4.3545045,2.120948506815,2.24626510942]},{"species":[{"element":"Mg","occu":1}],"abc":[0.5,0.756464999999999,0.257605],"properties":{"magmom":0.003},"label":"Mg","xyz":[4.3545045,6.588060493184992,2.24626510942]},{"species":[{"element":"Mg","occu":1}],"abc":[0.0,0.253425,0.744437999999999],"properties":{"magmom":0.002},"label":"Mg","xyz":[0.0,2.2070806058250003,6.491353450151991]},{"species":[{"element":"Mg","occu":1}],"abc":[0.0,0.746575,0.744437999999999],"properties":{"magmom":0.002},"label":"Mg","xyz":[0.0,6.501928394175,6.491353450151991]},{"species":[{"element":"Mg","occu":1}],"abc":[0.5,0.243535,0.742394999999999],"properties":{"magmom":0.003},"label":"Mg","xyz":[4.3545045,2.120948506815,6.4735388905799915]},{"species":[{"element":"Mg","occu":1}],"abc":[0.5,0.756464999999999,0.742394999999999],"properties":{"magmom":0.003},"label":"Mg","xyz":[4.3545045,6.588060493184992,6.4735388905799915]},{"species":[{"element":"Mg","occu":1}],"abc":[0.253425,0.0,0.255562],"properties":{"magmom":0.002},"label":"Mg","xyz":[2.2070806058250003,0.0,2.228450549848]},{"species":[{"element":"Mg","occu":1}],"abc":[0.243535,0.5,0.257605],"properties":{"magmom":0.003},"label":"Mg","xyz":[2.120948506815,4.3545045,2.24626510942]},{"species":[{"element":"Mg","occu":1}],"abc":[0.746575,0.0,0.255562],"properties":{"magmom":0.002},"label":"Mg","xyz":[6.501928394175,0.0,2.228450549848]},{"species":[{"element":"Mg","occu":1}],"abc":[0.756464999999999,0.5,0.257605],"properties":{"magmom":0.003},"label":"Mg","xyz":[6.588060493184992,4.3545045,2.24626510942]},{"species":[{"element":"Mg","occu":1}],"abc":[0.253425,0.0,0.744437999999999],"properties":{"magmom":0.002},"label":"Mg","xyz":[2.2070806058250003,0.0,6.491353450151991]},{"species":[{"element":"Mg","occu":1}],"abc":[0.243535,0.5,0.742394999999999],"properties":{"magmom":0.003},"label":"Mg","xyz":[2.120948506815,4.3545045,6.4735388905799915]},{"species":[{"element":"Mg","occu":1}],"abc":[0.746575,0.0,0.744437999999999],"properties":{"magmom":0.002},"label":"Mg","xyz":[6.501928394175,0.0,6.491353450151991]},{"species":[{"element":"Mg","occu":1}],"abc":[0.756464999999999,0.5,0.742394999999999],"properties":{"magmom":0.003},"label":"Mg","xyz":[6.588060493184992,4.3545045,6.4735388905799915]},{"species":[{"element":"Sn","occu":1}],"abc":[0.0,0.0,0.0],"properties":{"magmom":0.018000000000000002},"label":"Sn","xyz":[0.0,0.0,0.0]},{"species":[{"element":"Bi","occu":1}],"abc":[0.5,0.5,0.0],"properties":{"magmom":0.114},"label":"Bi","xyz":[4.3545045,4.3545045,0.0]},{"species":[{"element":"O","occu":1}],"abc":[0.0,0.0,0.271221999999999],"properties":{"magmom":0.005},"label":"O","xyz":[0.0,0.0,2.3650026804879913]},{"species":[{"element":"O","occu":1}],"abc":[0.0,0.5,0.25619000000000003],"properties":{"magmom":0.002},"label":"O","xyz":[0.0,4.3545045,2.2339265867600004]},{"species":[{"element":"O","occu":1}],"abc":[0.5,0.0,0.25619000000000003],"properties":{"magmom":0.002},"label":"O","xyz":[4.3545045,0.0,2.2339265867600004]},{"species":[{"element":"O","occu":1}],"abc":[0.5,0.5,0.270635],"properties":{"magmom":0.021},"label":"O","xyz":[4.3545045,4.3545045,2.35988415554]},{"species":[{"element":"O","occu":1}],"abc":[0.0,0.0,0.728777999999999],"properties":{"magmom":0.005},"label":"O","xyz":[0.0,0.0,6.354801319511991]},{"species":[{"element":"O","occu":1}],"abc":[0.0,0.5,0.7438100000000001],"properties":{"magmom":0.002},"label":"O","xyz":[0.0,4.3545045,6.485877413240001]},{"species":[{"element":"O","occu":1}],"abc":[0.5,0.0,0.7438100000000001],"properties":{"magmom":0.002},"label":"O","xyz":[4.3545045,0.0,6.485877413240001]},{"species":[{"element":"O","occu":1}],"abc":[0.5,0.5,0.729364999999999],"properties":{"magmom":0.021},"label":"O","xyz":[4.3545045,4.3545045,6.359919844459991]},{"species":[{"element":"O","occu":1}],"abc":[0.250052999999999,0.250052999999999,0.248835],"properties":{"magmom":0.003},"label":"O","xyz":[2.1777138274769916,2.1777138274769916,2.16979242834]},{"species":[{"element":"O","occu":1}],"abc":[0.250052999999999,0.749946999999999,0.248835],"properties":{"magmom":0.003},"label":"O","xyz":[2.1777138274769916,6.5312951725229915,2.16979242834]},{"species":[{"element":"O","occu":1}],"abc":[0.749946999999999,0.250052999999999,0.248835],"properties":{"magmom":0.003},"label":"O","xyz":[6.5312951725229915,2.1777138274769916,2.16979242834]},{"species":[{"element":"O","occu":1}],"abc":[0.749946999999999,0.749946999999999,0.248835],"properties":{"magmom":0.003},"label":"O","xyz":[6.5312951725229915,6.5312951725229915,2.16979242834]},{"species":[{"element":"O","occu":1}],"abc":[0.250052999999999,0.250052999999999,0.751165],"properties":{"magmom":0.003},"label":"O","xyz":[2.1777138274769916,2.1777138274769916,6.55001157166]},{"species":[{"element":"O","occu":1}],"abc":[0.250052999999999,0.749946999999999,0.751165],"properties":{"magmom":0.003},"label":"O","xyz":[2.1777138274769916,6.5312951725229915,6.55001157166]},{"species":[{"element":"O","occu":1}],"abc":[0.749946999999999,0.250052999999999,0.751165],"properties":{"magmom":0.003},"label":"O","xyz":[6.5312951725229915,2.1777138274769916,6.55001157166]},{"species":[{"element":"O","occu":1}],"abc":[0.749946999999999,0.749946999999999,0.751165],"properties":{"magmom":0.003},"label":"O","xyz":[6.5312951725229915,6.5312951725229915,6.55001157166]},{"species":[{"element":"O","occu":1}],"abc":[0.0,0.269467,0.0],"properties":{"magmom":0.003},"label":"O","xyz":[0.0,2.346790528203,0.0]},{"species":[{"element":"O","occu":1}],"abc":[0.0,0.730533,0.0],"properties":{"magmom":0.003},"label":"O","xyz":[0.0,6.362218471797,0.0]},{"species":[{"element":"O","occu":1}],"abc":[0.5,0.232816,0.0],"properties":{"magmom":0.012},"label":"O","xyz":[4.3545045,2.027596639344,0.0]},{"species":[{"element":"O","occu":1}],"abc":[0.5,0.767184,0.0],"properties":{"magmom":0.012},"label":"O","xyz":[4.3545045,6.681412360656,0.0]},{"species":[{"element":"O","occu":1}],"abc":[0.0,0.252791999999999,0.5],"properties":{"magmom":0.002},"label":"O","xyz":[0.0,2.2015678031279915,4.359902]},{"species":[{"element":"O","occu":1}],"abc":[0.0,0.747208,0.5],"properties":{"magmom":0.002},"label":"O","xyz":[0.0,6.507441196872,4.359902]},{"species":[{"element":"O","occu":1}],"abc":[0.5,0.24741000000000002,0.5],"properties":{"magmom":0.003},"label":"O","xyz":[4.3545045,2.15469591669,4.359902]},{"species":[{"element":"O","occu":1}],"abc":[0.5,0.7525900000000001,0.5],"properties":{"magmom":0.003},"label":"O","xyz":[4.3545045,6.554313083310001,4.359902]},{"species":[{"element":"O","occu":1}],"abc":[0.269467,0.0,0.0],"properties":{"magmom":0.003},"label":"O","xyz":[2.346790528203,0.0,0.0]},{"species":[{"element":"O","occu":1}],"abc":[0.232816,0.5,0.0],"properties":{"magmom":0.012},"label":"O","xyz":[2.027596639344,4.3545045,0.0]},{"species":[{"element":"O","occu":1}],"abc":[0.730533,0.0,0.0],"properties":{"magmom":0.003},"label":"O","xyz":[6.362218471797,0.0,0.0]},{"species":[{"element":"O","occu":1}],"abc":[0.767184,0.5,0.0],"properties":{"magmom":0.012},"label":"O","xyz":[6.681412360656,4.3545045,0.0]},{"species":[{"element":"O","occu":1}],"abc":[0.252791999999999,0.0,0.5],"properties":{"magmom":0.002},"label":"O","xyz":[2.2015678031279915,0.0,4.359902]},{"species":[{"element":"O","occu":1}],"abc":[0.24741000000000002,0.5,0.5],"properties":{"magmom":0.003},"label":"O","xyz":[2.15469591669,4.3545045,4.359902]},{"species":[{"element":"O","occu":1}],"abc":[0.747208,0.0,0.5],"properties":{"magmom":0.002},"label":"O","xyz":[6.507441196872,0.0,4.359902]},{"species":[{"element":"O","occu":1}],"abc":[0.7525900000000001,0.5,0.5],"properties":{"magmom":0.003},"label":"O","xyz":[6.554313083310001,4.3545045,4.359902]}]}